Metadata-Version: 2.1
Name: SpendScheme
Version: 0.5
Summary: SpendScheme is a microframework for text formatting in Python 3
Home-page: https://github.com/Jupiter404E/SpendScheme
Author: Jupiter404E
License: MPL-2.0 license
Project-URL: Documentation (GitHub), https://github.com/Jupiter404E/SpendScheme/blob/main/README.md
Project-URL: Source (GitHub), https://github.com/Jupiter404E/SpendScheme
Classifier: License :: OSI Approved :: Mozilla Public License 2.0 (MPL 2.0)
Classifier: Intended Audience :: Developers
Classifier: Natural Language :: English
Classifier: Operating System :: OS Independent
Classifier: Programming Language :: Python :: 3.8
Classifier: Programming Language :: Python :: 3.9
Classifier: Programming Language :: Python :: 3.10
Classifier: Programming Language :: Python :: Implementation :: CPython
Classifier: Topic :: Communications :: Chat
Classifier: Topic :: Internet :: WWW/HTTP
Classifier: Topic :: Internet
Classifier: Topic :: Software Development :: Libraries
Classifier: Topic :: Software Development :: Libraries :: Application Frameworks
Classifier: Topic :: Software Development :: Libraries :: Python Modules
Classifier: Topic :: Utilities
Classifier: Typing :: Typed
Requires-Python: >=3.8
License-File: LICENSE.txt
